odoo/addons/l10n_it_sct_cbi/README.rst
odoo/addons/l10n_it_sct_cbi/__init__.py
odoo/addons/l10n_it_sct_cbi/__manifest__.py
odoo/addons/l10n_it_sct_cbi/data/account_payment_method.xml
odoo/addons/l10n_it_sct_cbi/data/standards/CBIBdyCrossBorderPaymentRequest.00.01.01.xsd
odoo/addons/l10n_it_sct_cbi/data/standards/CBIBdyPaymentRequest.00.04.01.xsd
odoo/addons/l10n_it_sct_cbi/data/standards/CBICrossBorderPaymentRequestLogMsg.00.01.01.xsd
odoo/addons/l10n_it_sct_cbi/data/standards/CBICrossBorderPaymentRequestPhyMsg.00.01.01.xsd
odoo/addons/l10n_it_sct_cbi/data/standards/CBIHdrSrv.001.07.xsd
odoo/addons/l10n_it_sct_cbi/data/standards/CBIHdrTrt.001.07.xsd
odoo/addons/l10n_it_sct_cbi/data/standards/CBIPaymentRequest.00.04.01.xsd
odoo/addons/l10n_it_sct_cbi/data/standards/CBIPaymentRequestMsg.00.04.01.xsd
odoo/addons/l10n_it_sct_cbi/data/standards/CBISgnInf.001.04.xsd
odoo/addons/l10n_it_sct_cbi/i18n/it.po
odoo/addons/l10n_it_sct_cbi/i18n/l10n_it_sct_cbi.pot
odoo/addons/l10n_it_sct_cbi/i18n/sl.po
odoo/addons/l10n_it_sct_cbi/models/__init__.py
odoo/addons/l10n_it_sct_cbi/models/account_payment_method.py
odoo/addons/l10n_it_sct_cbi/models/account_payment_order.py
odoo/addons/l10n_it_sct_cbi/readme/CONFIGURE.md
odoo/addons/l10n_it_sct_cbi/readme/CONTRIBUTORS.md
odoo/addons/l10n_it_sct_cbi/readme/DESCRIPTION.md
odoo/addons/l10n_it_sct_cbi/readme/USAGE.md
odoo/addons/l10n_it_sct_cbi/static/company_setting.png
odoo/addons/l10n_it_sct_cbi/static/generate_payment.png
odoo/addons/l10n_it_sct_cbi/static/make_payment_download.png
odoo/addons/l10n_it_sct_cbi/static/order_payment.png
odoo/addons/l10n_it_sct_cbi/static/payment_mode1.png
odoo/addons/l10n_it_sct_cbi/static/payment_mode2.png
odoo/addons/l10n_it_sct_cbi/static/description/icon.png
odoo/addons/l10n_it_sct_cbi/static/description/index.html
odoo/addons/l10n_it_sct_cbi/tests/__init__.py
odoo/addons/l10n_it_sct_cbi/tests/test_generate_file.py
odoo_addon_l10n_it_sct_cbi-16.0.1.0.2.dist-info/METADATA
odoo_addon_l10n_it_sct_cbi-16.0.1.0.2.dist-info/WHEEL
odoo_addon_l10n_it_sct_cbi-16.0.1.0.2.dist-info/top_level.txt
odoo_addon_l10n_it_sct_cbi-16.0.1.0.2.dist-info/RECORD
