Metadata-Version: 2.1
Name: odoo-addon-l10n_it_sct_cbi
Version: 16.0.1.0.2
Requires-Python: >=3.10
Requires-Dist: odoo-addon-account_banking_pain_base>=16.0dev,<16.1dev
Requires-Dist: odoo>=16.0a,<16.1dev
Summary: Usare gli standard CBI per SEPA Credit Transfer
Home-page: https://github.com/OCA/l10n-italy/tree/16.0/l10n_it_sct_cbi
License: AGPL-3
Author: Openforce di Alessandro Camilli, Odoo Community Association (OCA)
Author-email: support@odoo-community.org
Classifier: Programming Language :: Python
Classifier: Framework :: Odoo
Classifier: Framework :: Odoo :: 16.0
Classifier: License :: OSI Approved :: GNU Affero General Public License v3
